odoo/addons/stock_product_qty_by_packaging/README.rst
odoo/addons/stock_product_qty_by_packaging/__init__.py
odoo/addons/stock_product_qty_by_packaging/__manifest__.py
odoo/addons/stock_product_qty_by_packaging/i18n/it.po
odoo/addons/stock_product_qty_by_packaging/i18n/stock_product_qty_by_packaging.pot
odoo/addons/stock_product_qty_by_packaging/models/__init__.py
odoo/addons/stock_product_qty_by_packaging/models/stock_inventory_line.py
odoo/addons/stock_product_qty_by_packaging/models/stock_move.py
odoo/addons/stock_product_qty_by_packaging/models/stock_move_line.py
odoo/addons/stock_product_qty_by_packaging/models/stock_quant.py
odoo/addons/stock_product_qty_by_packaging/readme/CONTRIBUTORS.rst
odoo/addons/stock_product_qty_by_packaging/readme/CREDITS.rst
odoo/addons/stock_product_qty_by_packaging/readme/DESCRIPTION.rst
odoo/addons/stock_product_qty_by_packaging/static/description/icon.png
odoo/addons/stock_product_qty_by_packaging/static/description/index.html
odoo/addons/stock_product_qty_by_packaging/tests/__init__.py
odoo/addons/stock_product_qty_by_packaging/tests/test_stock.py
odoo/addons/stock_product_qty_by_packaging/views/stock_inventory_line.xml
odoo/addons/stock_product_qty_by_packaging/views/stock_picking.xml
odoo14_addon_stock_product_qty_by_packaging-14.0.1.0.1.dev6.dist-info/METADATA
odoo14_addon_stock_product_qty_by_packaging-14.0.1.0.1.dev6.dist-info/WHEEL
odoo14_addon_stock_product_qty_by_packaging-14.0.1.0.1.dev6.dist-info/top_level.txt
odoo14_addon_stock_product_qty_by_packaging-14.0.1.0.1.dev6.dist-info/RECORD
